electromyogram/__init__.py
electromyogram/consts.py
electromyogram/face_model.h5
electromyogram/plot.py
electromyogram/schemes.py
electromyogram/utils.py
electromyogram-1.1.3.dist-info/LICENSE.txt
electromyogram-1.1.3.dist-info/METADATA
electromyogram-1.1.3.dist-info/WHEEL
electromyogram-1.1.3.dist-info/top_level.txt
electromyogram-1.1.3.dist-info/RECORD
