Metadata-Version: 2.1
Name: electromyogram
Version: 1.1.3
Summary: This is a small python package to create a Electromyogram (EMG) Intensity plots for facial muscles with facial structure.
Home-page: https://inf-cv.uni-jena.de/home/research/learning3d/facial-paresis-analysis/
Author: Tim Büchner
Author-email: tim.buechner@uni-jena.de
License: MIT
Project-URL: Source, https://github.com/cvjena/electromyogram
Project-URL: Tracker, https://github.com/cvjena/electromyogram/issues
Platform: any
Classifier: Development Status :: 5 - Production/Stable
Classifier: Programming Language :: Python
Requires-Python: >=3.9
License-File: LICENSE.txt
Requires-Dist: numpy <2,>=1.23
Requires-Dist: opencv-python-headless <5,>=4.5
Requires-Dist: scipy <2,>=1.8
Requires-Dist: palettable >3.3
Requires-Dist: matplotlib <4,>=3.5
Requires-Dist: h5py >=3.10
Provides-Extra: testing
Requires-Dist: setuptools ; extra == 'testing'
Requires-Dist: pytest ; extra == 'testing'
Requires-Dist: pytest-cov ; extra == 'testing'
